su_run/__init__.py
su_run/process.py
su_run/su.py
su_run-0.0.2.dist-info/METADATA
su_run-0.0.2.dist-info/WHEEL
su_run-0.0.2.dist-info/top_level.txt
su_run-0.0.2.dist-info/RECORD
