Metadata-Version: 2.1
Name: su-run
Version: 0.0.2
Summary: Run a subprocess as different user
Author: Clayton Voges
Author-email: vogesclayton@gmail.com
